{"namedChunkGroups":{"polyfill":{"name":"polyfill","assets":[{"name":"webpack-runtime-e4e37ede0192298f0ddd.js","size":3810},{"name":"polyfill-3cb2f59a28476a237ea5.js","size":82645}],"filteredAssets":0,"assetsSize":86455,"filteredAuxiliaryAssets":2,"auxiliaryAssetsSize":217020},"app":{"name":"app","assets":[{"name":"webpack-runtime-e4e37ede0192298f0ddd.js","size":3810},{"name":"framework-05fa0cd689ddc32737a6.js","size":129746},{"name":"app-92c0c82a668e248c68ad.js","size":74153}],"filteredAssets":0,"assetsSize":207709,"filteredAuxiliaryAssets":3,"auxiliaryAssetsSize":666692},"component---src-pages-404-js":{"name":"component---src-pages-404-js","assets":[{"name":"component---src-pages-404-js-e9d1a51bb23a4e78ae0d.js","size":820}],"filteredAssets":0,"assetsSize":820,"filteredAuxiliaryAssets":1,"auxiliaryAssetsSize":1889},"component---src-pages-index-js":{"name":"component---src-pages-index-js","assets":[{"name":"component---src-pages-index-js-36039f073238722f4b5e.js","size":4558}],"filteredAssets":0,"assetsSize":4558,"filteredAuxiliaryAssets":1,"auxiliaryAssetsSize":7607}},"assetsByChunkName":{"polyfill":["webpack-runtime-e4e37ede0192298f0ddd.js","polyfill-3cb2f59a28476a237ea5.js"],"app":["webpack-runtime-e4e37ede0192298f0ddd.js","framework-05fa0cd689ddc32737a6.js","app-92c0c82a668e248c68ad.js"],"component---src-pages-404-js":["component---src-pages-404-js-e9d1a51bb23a4e78ae0d.js"],"component---src-pages-index-js":["component---src-pages-index-js-36039f073238722f4b5e.js"]},"childAssetsByChunkName":{}}